duck_chat_api/__init__.py
duck_chat_api/api.py
duck_chat_api/event.py
duck_chat_api/exceptions.py
duck_chat_api/extra.py
duck_chat_api/model_type.py
duck_chat_api/parts.py
duck_chat_api/request_data.py
duck_chat_api/service/__main__.py
duck_chat_api/service/headers_manager.py
duck_chat_api/service/service.py
duck_chat_api/service/utils.py
duck_chat_api/utils/__init__.py
duck_chat_api/utils/headers.py
duck_chat_api/utils/models.py
duck_chat_api-0.2.1.dist-info/METADATA
duck_chat_api-0.2.1.dist-info/WHEEL
duck_chat_api-0.2.1.dist-info/entry_points.txt
duck_chat_api-0.2.1.dist-info/RECORD
