Metadata-Version: 2.4
Name: duck_chat_api
Version: 0.2.1
Summary: DuckDuckGo Chat AI client
Author: paranoik1
Author-email: paranoik@duck.com
Requires-Python: >=3.13
Classifier: Programming Language :: Python :: 3
Classifier: Programming Language :: Python :: 3.13
Classifier: Programming Language :: Python :: 3.14
Requires-Dist: aiohttp (>=3.12.15,<4.0.0)
Requires-Dist: bs4 (>=0.0.2,<0.0.3)
Requires-Dist: msgspec (>=0.19.0,<0.20.0)
